moelog/__init__.py
moelog/__main.py
moelog-0.0.0.3.dist-info/DESCRIPTION.rst
moelog-0.0.0.3.dist-info/METADATA
moelog-0.0.0.3.dist-info/RECORD
moelog-0.0.0.3.dist-info/WHEEL
moelog-0.0.0.3.dist-info/metadata.json
moelog-0.0.0.3.dist-info/top_level.txt
