Metadata-Version: 2.0
Name: moelog
Version: 0.0.0.3
Summary: A easy to use Logger
Home-page: https://github.com/moe001/moelog
Author: moe001
Author-email: i@001.moe
License: MIT
Platform: UNKNOWN
